[{"username":"a","group":"registered"},{"username":"asf","group":"guest"},{"username":"f","group":null,"password":""},{"username":"e","group":"guest"},{"username":"a","group":"registered"},{"username":"w","group":null,"password":"w"},{"username":"w","group":"guest"},{"username":"a","group":null,"password":"0cc175b9c0f1b6a831c399e269772661"},{"username":"rwr","group":"guest"},{"username":"wf","group":null,"password":"c1b291cb8522236e421731b509c9fcdd"},{"username":"wff","group":null,"password":"b000412432f4de8933c8f6fbed36ba94"},{"username":"a","group":null,"password":"0cc175b9c0f1b6a831c399e269772661"},{"username":"wff","group":null,"password":"b000412432f4de8933c8f6fbed36ba94"},{"username":"wffff","group":"guest"},{"username":"wff","group":null,"password":"b000412432f4de8933c8f6fbed36ba94"},{"username":"wff","group":null,"password":"b000412432f4de8933c8f6fbed36ba94"},{"username":"w","group":null,"password":"f1290186a5d0b1ceab27f4e77c0c5d68"},{"username":"w","group":null,"password":"f1290186a5d0b1ceab27f4e77c0c5d68"},{"username":"aa","group":null,"password":"4124bc0a9335c27f086f24ba207a4912"},{"username":"wff2","group":null,"password":"ec4f9fdcddc3c83e88c2cf3f26dfc100"}]